HelloProject/__init__.py
HelloProject/hello.py
happypeopleyeah-1.1.0.dist-info/METADATA
happypeopleyeah-1.1.0.dist-info/WHEEL
happypeopleyeah-1.1.0.dist-info/top_level.txt
happypeopleyeah-1.1.0.dist-info/RECORD
