Metadata-Version: 2.1
Name: happypeopleyeah
Version: 1.1.0
Summary: This is just a nice experiment. And it works well.
Home-page: https://github.com/your-username/your-repo
Author: Baholo Mokoena
Author-email: mokoenabaholo90@gmail.com
Classifier: Programming Language :: Python :: 3
Classifier: Operating System :: OS Independent
Requires-Python: >=3.8
